limeclient/haldocument.py
limeclient/importconfig.py
limeclient/importfile.py
limeclient/importjob.py
limeclient/limeclient.py
limeclient/limetypes.py
limeclient/__init__.py
limeclient-1.0.3.dist-info/DESCRIPTION.rst
limeclient-1.0.3.dist-info/METADATA
limeclient-1.0.3.dist-info/metadata.json
limeclient-1.0.3.dist-info/RECORD
limeclient-1.0.3.dist-info/top_level.txt
limeclient-1.0.3.dist-info/WHEEL
