Metadata-Version: 2.0
Name: limeclient
Version: 1.0.3
Summary: Python client for the LIME Pro API
Home-page: UNKNOWN
Author: Lundalogik AB
Author-email: info@lundalogik.se
License: MPL 2.0
Platform: UNKNOWN
Classifier: Development Status :: 4 - Beta
Classifier: License :: OSI Approved :: Mozilla Public License 2.0 (MPL 2.0)
Classifier: Programming Language :: Python :: 3
Requires-Dist: requests (>=2.4.3)
